h_api/__init__.py
h_api/enums.py
h_api/exceptions.py
h_api/schema.py
h_api/bulk_api/__init__.py
h_api/bulk_api/command_batcher.py
h_api/bulk_api/command_builder.py
h_api/bulk_api/command_processor.py
h_api/bulk_api/entry_point.py
h_api/bulk_api/executor.py
h_api/bulk_api/id_references.py
h_api/bulk_api/observer.py
h_api/bulk_api/model/__init__.py
h_api/bulk_api/model/command.py
h_api/bulk_api/model/config_body.py
h_api/bulk_api/model/data_body.py
h_api/bulk_api/model/report.py
h_api/model/__init__.py
h_api/model/base.py
h_api/model/json_api.py
h_api/resources/schema/core.json
h_api/resources/schema/json_api.json
h_api/resources/schema/bulk_api/wrapper.json
h_api/resources/schema/bulk_api/command/configuration.json
h_api/resources/schema/bulk_api/command/create_group_membership.json
h_api/resources/schema/bulk_api/command/upsert_group.json
h_api/resources/schema/bulk_api/command/upsert_user.json
h_api-1.1.1.dist-info/LICENSE
h_api-1.1.1.dist-info/METADATA
h_api-1.1.1.dist-info/WHEEL
h_api-1.1.1.dist-info/top_level.txt
h_api-1.1.1.dist-info/RECORD
