Metadata-Version: 2.2
Name: h-api
Version: 1.1.1
Summary: Tools and components for calling the H API.
Home-page: https://github.com/hypothesis/h-api
Project-URL: Bug Tracker, https://github.com/hypothesis/h-api/issues
Project-URL: Changelog, https://github.com/hypothesis/h-api/releases
Classifier: Programming Language :: Python :: 3
Classifier: License :: OSI Approved :: BSD License
Classifier: Intended Audience :: Developers
Requires-Python: >=3.9
License-File: LICENSE
Requires-Dist: jsonschema>=4.18
Requires-Dist: importlib_resources
Requires-Dist: referencing
